{
  "info": {
    "_postman_id": "e3bd656f-0e36-41bb-8fc8-2dd1715a04b4",
    "name": "OR Tracking API",
    "description": "Operating Theatre Patient Tracking System — full API test suite.\n\nBefore running:\n1. Start the server: pnpm dev (port 3000)\n2. Run 'Login' first — it automatically saves the JWT to {{token}}\n3. Collection variables: baseUrl, token, visitId, roomId, userId, familyToken",
    "schema": "https://schema.getpostman.com/json/collection/v2.1.0/collection.json",
    "_exporter_id": "52917534",
    "_collection_link": "https://go.postman.co/collection/52917534-e3bd656f-0e36-41bb-8fc8-2dd1715a04b4?source=collection_link"
  },
  "item": [
    {
      "name": "Auth",
      "item": [
        {
          "name": "Login",
          "event": [
            {
              "listen": "test",
              "script": {
                "exec": [
                  "pm.test('Status 200', () => pm.response.to.have.status(200));",
                  "pm.test('Returns token', () => {",
                  "  const json = pm.response.json();",
                  "  pm.expect(json).to.have.property('token');",
                  "  pm.expect(json.user).to.have.property('role');",
                  "  pm.collectionVariables.set('token', json.token);",
                  "});"
                ],
                "type": "text/javascript"
              }
            }
          ],
          "request": {
            "method": "POST",
            "header": [
              {
                "key": "Content-Type",
                "value": "application/json"
              }
            ],
            "body": {
              "mode": "raw",
              "raw": "{\n  \"username\": \"admin\",\n  \"password\": \"admin123\"\n}"
            },
            "url": {
              "raw": "{{baseUrl}}/auth/login",
              "host": [
                "{{baseUrl}}"
              ],
              "path": [
                "auth",
                "login"
              ]
            }
          },
          "response": []
        },
        {
          "name": "Login — wrong password (expect 401)",
          "event": [
            {
              "listen": "test",
              "script": {
                "exec": [
                  "pm.test('Status 401', () => pm.response.to.have.status(401));"
                ],
                "type": "text/javascript"
              }
            }
          ],
          "request": {
            "method": "POST",
            "header": [
              {
                "key": "Content-Type",
                "value": "application/json"
              }
            ],
            "body": {
              "mode": "raw",
              "raw": "{\n  \"username\": \"admin\",\n  \"password\": \"wrongpassword\"\n}"
            },
            "url": {
              "raw": "{{baseUrl}}/auth/login",
              "host": [
                "{{baseUrl}}"
              ],
              "path": [
                "auth",
                "login"
              ]
            }
          },
          "response": []
        },
        {
          "name": "Get Current User",
          "event": [
            {
              "listen": "test",
              "script": {
                "exec": [
                  "pm.test('Status 200', () => pm.response.to.have.status(200));",
                  "pm.test('Returns user', () => {",
                  "  const json = pm.response.json();",
                  "  pm.expect(json.user).to.have.property('username');",
                  "  pm.expect(json.user).to.have.property('role');",
                  "});"
                ],
                "type": "text/javascript"
              }
            }
          ],
          "request": {
            "method": "GET",
            "header": [
              {
                "key": "Authorization",
                "value": "Bearer {{token}}"
              }
            ],
            "url": {
              "raw": "{{baseUrl}}/auth/me",
              "host": [
                "{{baseUrl}}"
              ],
              "path": [
                "auth",
                "me"
              ]
            }
          },
          "response": []
        },
        {
          "name": "Get Current User — no token (expect 401)",
          "event": [
            {
              "listen": "test",
              "script": {
                "exec": [
                  "pm.test('Status 401', () => pm.response.to.have.status(401));"
                ],
                "type": "text/javascript"
              }
            }
          ],
          "request": {
            "method": "GET",
            "header": [],
            "url": {
              "raw": "{{baseUrl}}/auth/me",
              "host": [
                "{{baseUrl}}"
              ],
              "path": [
                "auth",
                "me"
              ]
            }
          },
          "response": []
        },
        {
          "name": "Logout",
          "event": [
            {
              "listen": "test",
              "script": {
                "exec": [
                  "pm.test('Status 200', () => pm.response.to.have.status(200));"
                ],
                "type": "text/javascript"
              }
            }
          ],
          "request": {
            "method": "POST",
            "header": [
              {
                "key": "Authorization",
                "value": "Bearer {{token}}"
              }
            ],
            "url": {
              "raw": "{{baseUrl}}/auth/logout",
              "host": [
                "{{baseUrl}}"
              ],
              "path": [
                "auth",
                "logout"
              ]
            }
          },
          "response": []
        },
        {
          "name": "Use token after logout (expect 401)",
          "event": [
            {
              "listen": "test",
              "script": {
                "exec": [
                  "pm.test('Status 401 — token revoked', () => pm.response.to.have.status(401));"
                ],
                "type": "text/javascript"
              }
            }
          ],
          "request": {
            "method": "GET",
            "header": [
              {
                "key": "Authorization",
                "value": "Bearer {{token}}"
              }
            ],
            "url": {
              "raw": "{{baseUrl}}/auth/me",
              "host": [
                "{{baseUrl}}"
              ],
              "path": [
                "auth",
                "me"
              ]
            }
          },
          "response": []
        }
      ]
    },
    {
      "name": "Visits",
      "item": [
        {
          "name": "List Visits",
          "event": [
            {
              "listen": "test",
              "script": {
                "exec": [
                  "pm.test('Status 200', () => pm.response.to.have.status(200));",
                  "pm.test('Returns visits array', () => {",
                  "  const json = pm.response.json();",
                  "  pm.expect(json).to.have.property('visits');",
                  "  pm.expect(json.visits).to.be.an('array');",
                  "});"
                ],
                "type": "text/javascript"
              }
            }
          ],
          "request": {
            "method": "GET",
            "header": [
              {
                "key": "Authorization",
                "value": "Bearer {{token}}"
              }
            ],
            "url": {
              "raw": "{{baseUrl}}/visits",
              "host": [
                "{{baseUrl}}"
              ],
              "path": [
                "visits"
              ],
              "query": [
                {
                  "key": "stage",
                  "value": "",
                  "disabled": true
                },
                {
                  "key": "active",
                  "value": "true",
                  "disabled": true
                },
                {
                  "key": "search",
                  "value": "",
                  "disabled": true
                }
              ]
            }
          },
          "response": []
        },
        {
          "name": "Create Visit",
          "event": [
            {
              "listen": "test",
              "script": {
                "exec": [
                  "pm.test('Status 201', () => pm.response.to.have.status(201));",
                  "pm.test('Returns visit with tracking ID', () => {",
                  "  const json = pm.response.json();",
                  "  pm.expect(json.visit).to.have.property('visit_tracking_id');",
                  "  pm.expect(json.visit.visit_tracking_id).to.match(/^VT-/);",
                  "  pm.collectionVariables.set('visitId', json.visit.id);",
                  "});"
                ],
                "type": "text/javascript"
              }
            }
          ],
          "request": {
            "method": "POST",
            "header": [
              {
                "key": "Authorization",
                "value": "Bearer {{token}}"
              },
              {
                "key": "Content-Type",
                "value": "application/json"
              }
            ],
            "body": {
              "mode": "raw",
              "raw": "{\n  \"patient\": {\n    \"mrn\": \"MRN-TEST-001\",\n    \"first_name\": \"Test\",\n    \"last_name\": \"Patient\",\n    \"date_of_birth\": \"1985-06-15\",\n    \"gender\": \"male\"\n  },\n  \"family_contact\": {\n    \"name\": \"Test Contact\",\n    \"phone\": \"+447700900001\",\n    \"relationship\": \"spouse\",\n    \"email\": \"contact@example.com\",\n    \"consent_given\": true\n  }\n}"
            },
            "url": {
              "raw": "{{baseUrl}}/visits",
              "host": [
                "{{baseUrl}}"
              ],
              "path": [
                "visits"
              ]
            }
          },
          "response": []
        },
        {
          "name": "Create Visit — missing required fields (expect 400)",
          "event": [
            {
              "listen": "test",
              "script": {
                "exec": [
                  "pm.test('Status 400', () => pm.response.to.have.status(400));"
                ],
                "type": "text/javascript"
              }
            }
          ],
          "request": {
            "method": "POST",
            "header": [
              {
                "key": "Authorization",
                "value": "Bearer {{token}}"
              },
              {
                "key": "Content-Type",
                "value": "application/json"
              }
            ],
            "body": {
              "mode": "raw",
              "raw": "{\n  \"patient\": {\n    \"first_name\": \"No MRN\"\n  }\n}"
            },
            "url": {
              "raw": "{{baseUrl}}/visits",
              "host": [
                "{{baseUrl}}"
              ],
              "path": [
                "visits"
              ]
            }
          },
          "response": []
        },
        {
          "name": "Get Visit by ID",
          "event": [
            {
              "listen": "test",
              "script": {
                "exec": [
                  "pm.test('Status 200', () => pm.response.to.have.status(200));",
                  "pm.test('Returns visit', () => {",
                  "  const json = pm.response.json();",
                  "  pm.expect(json.visit).to.have.property('visit_tracking_id');",
                  "  pm.expect(json.visit).to.have.property('current_stage');",
                  "});"
                ],
                "type": "text/javascript"
              }
            }
          ],
          "request": {
            "method": "GET",
            "header": [
              {
                "key": "Authorization",
                "value": "Bearer {{token}}"
              }
            ],
            "url": {
              "raw": "{{baseUrl}}/visits/{{visitId}}",
              "host": [
                "{{baseUrl}}"
              ],
              "path": [
                "visits",
                "{{visitId}}"
              ]
            }
          },
          "response": []
        },
        {
          "name": "Get Visit — not found (expect 404)",
          "event": [
            {
              "listen": "test",
              "script": {
                "exec": [
                  "pm.test('Status 404', () => pm.response.to.have.status(404));"
                ],
                "type": "text/javascript"
              }
            }
          ],
          "request": {
            "method": "GET",
            "header": [
              {
                "key": "Authorization",
                "value": "Bearer {{token}}"
              }
            ],
            "url": {
              "raw": "{{baseUrl}}/visits/99999",
              "host": [
                "{{baseUrl}}"
              ],
              "path": [
                "visits",
                "99999"
              ]
            }
          },
          "response": []
        },
        {
          "name": "Update Visit",
          "event": [
            {
              "listen": "test",
              "script": {
                "exec": [
                  "pm.test('Status 200', () => pm.response.to.have.status(200));"
                ],
                "type": "text/javascript"
              }
            }
          ],
          "request": {
            "method": "PUT",
            "header": [
              {
                "key": "Authorization",
                "value": "Bearer {{token}}"
              },
              {
                "key": "Content-Type",
                "value": "application/json"
              }
            ],
            "body": {
              "mode": "raw",
              "raw": "{\n  \"notes\": \"Updated via Postman\"\n}"
            },
            "url": {
              "raw": "{{baseUrl}}/visits/{{visitId}}",
              "host": [
                "{{baseUrl}}"
              ],
              "path": [
                "visits",
                "{{visitId}}"
              ]
            }
          },
          "response": []
        },
        {
          "name": "Update Stage",
          "event": [
            {
              "listen": "test",
              "script": {
                "exec": [
                  "pm.test('Status 200', () => pm.response.to.have.status(200));",
                  "pm.test('Stage updated', () => {",
                  "  const json = pm.response.json();",
                  "  pm.expect(json).to.have.property('visit');",
                  "});"
                ],
                "type": "text/javascript"
              }
            }
          ],
          "request": {
            "method": "PUT",
            "header": [
              {
                "key": "Authorization",
                "value": "Bearer {{token}}"
              },
              {
                "key": "Content-Type",
                "value": "application/json"
              }
            ],
            "body": {
              "mode": "raw",
              "raw": "{\n  \"to_stage_id\": 2\n}"
            },
            "url": {
              "raw": "{{baseUrl}}/visits/{{visitId}}/stage",
              "host": [
                "{{baseUrl}}"
              ],
              "path": [
                "visits",
                "{{visitId}}",
                "stage"
              ]
            }
          },
          "response": []
        },
        {
          "name": "Get Visit Timeline",
          "event": [
            {
              "listen": "test",
              "script": {
                "exec": [
                  "pm.test('Status 200', () => pm.response.to.have.status(200));",
                  "pm.test('Returns timeline array', () => {",
                  "  const json = pm.response.json();",
                  "  pm.expect(json).to.have.property('timeline');",
                  "  pm.expect(json.timeline).to.be.an('array');",
                  "});"
                ],
                "type": "text/javascript"
              }
            }
          ],
          "request": {
            "method": "GET",
            "header": [
              {
                "key": "Authorization",
                "value": "Bearer {{token}}"
              }
            ],
            "url": {
              "raw": "{{baseUrl}}/visits/{{visitId}}/timeline",
              "host": [
                "{{baseUrl}}"
              ],
              "path": [
                "visits",
                "{{visitId}}",
                "timeline"
              ]
            }
          },
          "response": []
        },
        {
          "name": "Delete Visit",
          "event": [
            {
              "listen": "test",
              "script": {
                "exec": [
                  "pm.test('Status 200', () => pm.response.to.have.status(200));"
                ],
                "type": "text/javascript"
              }
            }
          ],
          "request": {
            "method": "DELETE",
            "header": [
              {
                "key": "Authorization",
                "value": "Bearer {{token}}"
              }
            ],
            "url": {
              "raw": "{{baseUrl}}/visits/{{visitId}}",
              "host": [
                "{{baseUrl}}"
              ],
              "path": [
                "visits",
                "{{visitId}}"
              ]
            }
          },
          "response": []
        }
      ]
    },
    {
      "name": "Stages",
      "item": [
        {
          "name": "List All Stages",
          "event": [
            {
              "listen": "test",
              "script": {
                "exec": [
                  "pm.test('Status 200', () => pm.response.to.have.status(200));",
                  "pm.test('Returns stages array', () => {",
                  "  const json = pm.response.json();",
                  "  pm.expect(json).to.have.property('stages');",
                  "  pm.expect(json.stages).to.be.an('array');",
                  "  pm.expect(json.stages.length).to.be.above(0);",
                  "});"
                ],
                "type": "text/javascript"
              }
            }
          ],
          "request": {
            "method": "GET",
            "header": [
              {
                "key": "Authorization",
                "value": "Bearer {{token}}"
              }
            ],
            "url": {
              "raw": "{{baseUrl}}/stages",
              "host": [
                "{{baseUrl}}"
              ],
              "path": [
                "stages"
              ]
            }
          },
          "response": []
        }
      ]
    },
    {
      "name": "Rooms",
      "item": [
        {
          "name": "List All Rooms",
          "event": [
            {
              "listen": "test",
              "script": {
                "exec": [
                  "pm.test('Status 200', () => pm.response.to.have.status(200));",
                  "pm.test('Returns rooms array', () => {",
                  "  const json = pm.response.json();",
                  "  pm.expect(json).to.have.property('rooms');",
                  "  pm.expect(json.rooms).to.be.an('array');",
                  "});"
                ],
                "type": "text/javascript"
              }
            }
          ],
          "request": {
            "method": "GET",
            "header": [
              {
                "key": "Authorization",
                "value": "Bearer {{token}}"
              }
            ],
            "url": {
              "raw": "{{baseUrl}}/rooms",
              "host": [
                "{{baseUrl}}"
              ],
              "path": [
                "rooms"
              ]
            }
          },
          "response": []
        },
        {
          "name": "Get Room by ID",
          "event": [
            {
              "listen": "test",
              "script": {
                "exec": [
                  "pm.test('Status 200', () => pm.response.to.have.status(200));",
                  "pm.test('Returns room with status', () => {",
                  "  const json = pm.response.json();",
                  "  pm.expect(json.room).to.have.property('status');",
                  "});"
                ],
                "type": "text/javascript"
              }
            }
          ],
          "request": {
            "method": "GET",
            "header": [
              {
                "key": "Authorization",
                "value": "Bearer {{token}}"
              }
            ],
            "url": {
              "raw": "{{baseUrl}}/rooms/{{roomId}}",
              "host": [
                "{{baseUrl}}"
              ],
              "path": [
                "rooms",
                "{{roomId}}"
              ]
            }
          },
          "response": []
        },
        {
          "name": "Update Room Status",
          "event": [
            {
              "listen": "test",
              "script": {
                "exec": [
                  "pm.test('Status 200', () => pm.response.to.have.status(200));"
                ],
                "type": "text/javascript"
              }
            }
          ],
          "request": {
            "method": "PUT",
            "header": [
              {
                "key": "Authorization",
                "value": "Bearer {{token}}"
              },
              {
                "key": "Content-Type",
                "value": "application/json"
              }
            ],
            "body": {
              "mode": "raw",
              "raw": "{\n  \"status\": \"available\",\n  \"reason\": \"Manual override via Postman\"\n}"
            },
            "url": {
              "raw": "{{baseUrl}}/rooms/{{roomId}}/status",
              "host": [
                "{{baseUrl}}"
              ],
              "path": [
                "rooms",
                "{{roomId}}",
                "status"
              ]
            }
          },
          "response": []
        },
        {
          "name": "Start Cleaning Timer",
          "event": [
            {
              "listen": "test",
              "script": {
                "exec": [
                  "pm.test('Status 200', () => pm.response.to.have.status(200));"
                ],
                "type": "text/javascript"
              }
            }
          ],
          "request": {
            "method": "POST",
            "header": [
              {
                "key": "Authorization",
                "value": "Bearer {{token}}"
              },
              {
                "key": "Content-Type",
                "value": "application/json"
              }
            ],
            "body": {
              "mode": "raw",
              "raw": "{\n  \"duration_minutes\": 15\n}"
            },
            "url": {
              "raw": "{{baseUrl}}/rooms/{{roomId}}/cleaning/start",
              "host": [
                "{{baseUrl}}"
              ],
              "path": [
                "rooms",
                "{{roomId}}",
                "cleaning",
                "start"
              ]
            }
          },
          "response": []
        },
        {
          "name": "Complete Cleaning (Manual Override)",
          "event": [
            {
              "listen": "test",
              "script": {
                "exec": [
                  "pm.test('Status 200', () => pm.response.to.have.status(200));"
                ],
                "type": "text/javascript"
              }
            }
          ],
          "request": {
            "method": "POST",
            "header": [
              {
                "key": "Authorization",
                "value": "Bearer {{token}}"
              },
              {
                "key": "Content-Type",
                "value": "application/json"
              }
            ],
            "body": {
              "mode": "raw",
              "raw": "{\n  \"override_reason\": \"Room verified clean by charge nurse\"\n}"
            },
            "url": {
              "raw": "{{baseUrl}}/rooms/{{roomId}}/cleaning/complete",
              "host": [
                "{{baseUrl}}"
              ],
              "path": [
                "rooms",
                "{{roomId}}",
                "cleaning",
                "complete"
              ]
            }
          },
          "response": []
        }
      ]
    },
    {
      "name": "Barcode",
      "item": [
        {
          "name": "Generate Barcode",
          "event": [
            {
              "listen": "test",
              "script": {
                "exec": [
                  "pm.test('Status 200', () => pm.response.to.have.status(200));",
                  "pm.test('Returns barcode data', () => {",
                  "  const json = pm.response.json();",
                  "  pm.expect(json).to.have.property('barcode');",
                  "});"
                ],
                "type": "text/javascript"
              }
            }
          ],
          "request": {
            "method": "POST",
            "header": [
              {
                "key": "Authorization",
                "value": "Bearer {{token}}"
              },
              {
                "key": "Content-Type",
                "value": "application/json"
              }
            ],
            "body": {
              "mode": "raw",
              "raw": "{\n  \"visit_tracking_id\": \"VT-20260304-001\"\n}"
            },
            "url": {
              "raw": "{{baseUrl}}/barcode/generate",
              "host": [
                "{{baseUrl}}"
              ],
              "path": [
                "barcode",
                "generate"
              ]
            }
          },
          "response": []
        },
        {
          "name": "Scan Barcode",
          "event": [
            {
              "listen": "test",
              "script": {
                "exec": [
                  "pm.test('Status 200 or 404', () => {",
                  "  pm.expect(pm.response.code).to.be.oneOf([200, 404]);",
                  "});"
                ],
                "type": "text/javascript"
              }
            }
          ],
          "request": {
            "method": "POST",
            "header": [
              {
                "key": "Authorization",
                "value": "Bearer {{token}}"
              },
              {
                "key": "Content-Type",
                "value": "application/json"
              }
            ],
            "body": {
              "mode": "raw",
              "raw": "{\n  \"barcode_value\": \"VT-20260304-001\"\n}"
            },
            "url": {
              "raw": "{{baseUrl}}/barcode/scan",
              "host": [
                "{{baseUrl}}"
              ],
              "path": [
                "barcode",
                "scan"
              ]
            }
          },
          "response": []
        }
      ]
    },
    {
      "name": "Family Portal",
      "item": [
        {
          "name": "Request OTP",
          "event": [
            {
              "listen": "test",
              "script": {
                "exec": [
                  "pm.test('Status 200 or 404', () => {",
                  "  pm.expect(pm.response.code).to.be.oneOf([200, 404]);",
                  "});",
                  "pm.test('Response has delivery info if successful', () => {",
                  "  if (pm.response.code === 200) {",
                  "    const json = pm.response.json();",
                  "    pm.expect(json).to.have.property('delivery_method');",
                  "    pm.expect(json).to.have.property('masked_recipient');",
                  "  }",
                  "});"
                ],
                "type": "text/javascript"
              }
            }
          ],
          "request": {
            "method": "POST",
            "header": [
              {
                "key": "Content-Type",
                "value": "application/json"
              }
            ],
            "body": {
              "mode": "raw",
              "raw": "{\n  \"phone\": \"+447700900001\",\n  \"visit_tracking_id\": \"VT-20260304-001\"\n}"
            },
            "url": {
              "raw": "{{baseUrl}}/family/request-otp",
              "host": [
                "{{baseUrl}}"
              ],
              "path": [
                "family",
                "request-otp"
              ]
            }
          },
          "response": []
        },
        {
          "name": "Verify OTP",
          "event": [
            {
              "listen": "test",
              "script": {
                "exec": [
                  "pm.test('Status is 200 or 401', () => {",
                  "  pm.expect(pm.response.code).to.be.oneOf([200, 401, 423]);",
                  "});",
                  "if (pm.response.code === 200) {",
                  "  const json = pm.response.json();",
                  "  pm.collectionVariables.set('familyToken', json.token);",
                  "}"
                ],
                "type": "text/javascript"
              }
            }
          ],
          "request": {
            "method": "POST",
            "header": [
              {
                "key": "Content-Type",
                "value": "application/json"
              }
            ],
            "body": {
              "mode": "raw",
              "raw": "{\n  \"phone\": \"+447700900001\",\n  \"otp\": \"123456\"\n}"
            },
            "url": {
              "raw": "{{baseUrl}}/family/verify-otp",
              "host": [
                "{{baseUrl}}"
              ],
              "path": [
                "family",
                "verify-otp"
              ]
            }
          },
          "response": []
        },
        {
          "name": "Verify OTP — wrong code (expect 401)",
          "event": [
            {
              "listen": "test",
              "script": {
                "exec": [
                  "pm.test('Status 401 or 423', () => {",
                  "  pm.expect(pm.response.code).to.be.oneOf([401, 423]);",
                  "});"
                ],
                "type": "text/javascript"
              }
            }
          ],
          "request": {
            "method": "POST",
            "header": [
              {
                "key": "Content-Type",
                "value": "application/json"
              }
            ],
            "body": {
              "mode": "raw",
              "raw": "{\n  \"phone\": \"+447700900001\",\n  \"otp\": \"000000\"\n}"
            },
            "url": {
              "raw": "{{baseUrl}}/family/verify-otp",
              "host": [
                "{{baseUrl}}"
              ],
              "path": [
                "family",
                "verify-otp"
              ]
            }
          },
          "response": []
        },
        {
          "name": "Get Visit Status (family view)",
          "event": [
            {
              "listen": "test",
              "script": {
                "exec": [
                  "pm.test('Status 200 or 401', () => {",
                  "  pm.expect(pm.response.code).to.be.oneOf([200, 401]);",
                  "});",
                  "if (pm.response.code === 200) {",
                  "  pm.test('Returns limited data only', () => {",
                  "    const json = pm.response.json();",
                  "    pm.expect(json.patient).to.have.property('first_name');",
                  "    pm.expect(json.patient).to.not.have.property('last_name');",
                  "    pm.expect(json.patient).to.not.have.property('mrn');",
                  "    pm.expect(json.patient).to.not.have.property('date_of_birth');",
                  "    pm.expect(json).to.have.property('progress_percentage');",
                  "  });",
                  "}"
                ],
                "type": "text/javascript"
              }
            }
          ],
          "request": {
            "method": "GET",
            "header": [],
            "url": {
              "raw": "{{baseUrl}}/family/visit/{{familyToken}}",
              "host": [
                "{{baseUrl}}"
              ],
              "path": [
                "family",
                "visit",
                "{{familyToken}}"
              ]
            }
          },
          "response": []
        },
        {
          "name": "Get Visit Status — invalid token (expect 401)",
          "event": [
            {
              "listen": "test",
              "script": {
                "exec": [
                  "pm.test('Status 401', () => pm.response.to.have.status(401));"
                ],
                "type": "text/javascript"
              }
            }
          ],
          "request": {
            "method": "GET",
            "header": [],
            "url": {
              "raw": "{{baseUrl}}/family/visit/fam_invalid000000token",
              "host": [
                "{{baseUrl}}"
              ],
              "path": [
                "family",
                "visit",
                "fam_invalid000000token"
              ]
            }
          },
          "response": []
        }
      ]
    },
    {
      "name": "Users",
      "item": [
        {
          "name": "List Users",
          "event": [
            {
              "listen": "test",
              "script": {
                "exec": [
                  "pm.test('Status 200', () => pm.response.to.have.status(200));",
                  "pm.test('Returns users array', () => {",
                  "  const json = pm.response.json();",
                  "  pm.expect(json).to.have.property('users');",
                  "  pm.expect(json.users).to.be.an('array');",
                  "});"
                ],
                "type": "text/javascript"
              }
            }
          ],
          "request": {
            "method": "GET",
            "header": [
              {
                "key": "Authorization",
                "value": "Bearer {{token}}"
              }
            ],
            "url": {
              "raw": "{{baseUrl}}/users",
              "host": [
                "{{baseUrl}}"
              ],
              "path": [
                "users"
              ],
              "query": [
                {
                  "key": "role",
                  "value": "nurse",
                  "disabled": true
                },
                {
                  "key": "active",
                  "value": "true",
                  "disabled": true
                }
              ]
            }
          },
          "response": []
        },
        {
          "name": "Create User",
          "event": [
            {
              "listen": "test",
              "script": {
                "exec": [
                  "pm.test('Status 201', () => pm.response.to.have.status(201));",
                  "pm.test('Returns new user', () => {",
                  "  const json = pm.response.json();",
                  "  pm.expect(json.user).to.have.property('id');",
                  "  pm.expect(json.user).to.not.have.property('password_hash');",
                  "  pm.collectionVariables.set('userId', json.user.id);",
                  "});"
                ],
                "type": "text/javascript"
              }
            }
          ],
          "request": {
            "method": "POST",
            "header": [
              {
                "key": "Authorization",
                "value": "Bearer {{token}}"
              },
              {
                "key": "Content-Type",
                "value": "application/json"
              }
            ],
            "body": {
              "mode": "raw",
              "raw": "{\n  \"username\": \"testnurse\",\n  \"password\": \"Nurse123!\",\n  \"name\": \"Test Nurse\",\n  \"role\": \"nurse\",\n  \"email\": \"testnurse@hospital.nhs.uk\"\n}"
            },
            "url": {
              "raw": "{{baseUrl}}/users",
              "host": [
                "{{baseUrl}}"
              ],
              "path": [
                "users"
              ]
            }
          },
          "response": []
        },
        {
          "name": "Create User — duplicate username (expect 409)",
          "event": [
            {
              "listen": "test",
              "script": {
                "exec": [
                  "pm.test('Status 409', () => pm.response.to.have.status(409));"
                ],
                "type": "text/javascript"
              }
            }
          ],
          "request": {
            "method": "POST",
            "header": [
              {
                "key": "Authorization",
                "value": "Bearer {{token}}"
              },
              {
                "key": "Content-Type",
                "value": "application/json"
              }
            ],
            "body": {
              "mode": "raw",
              "raw": "{\n  \"username\": \"testnurse\",\n  \"password\": \"Nurse123!\",\n  \"name\": \"Duplicate\",\n  \"role\": \"nurse\"\n}"
            },
            "url": {
              "raw": "{{baseUrl}}/users",
              "host": [
                "{{baseUrl}}"
              ],
              "path": [
                "users"
              ]
            }
          },
          "response": []
        },
        {
          "name": "Update User",
          "event": [
            {
              "listen": "test",
              "script": {
                "exec": [
                  "pm.test('Status 200', () => pm.response.to.have.status(200));"
                ],
                "type": "text/javascript"
              }
            }
          ],
          "request": {
            "method": "PUT",
            "header": [
              {
                "key": "Authorization",
                "value": "Bearer {{token}}"
              },
              {
                "key": "Content-Type",
                "value": "application/json"
              }
            ],
            "body": {
              "mode": "raw",
              "raw": "{\n  \"name\": \"Test Nurse Updated\",\n  \"active\": false\n}"
            },
            "url": {
              "raw": "{{baseUrl}}/users/{{userId}}",
              "host": [
                "{{baseUrl}}"
              ],
              "path": [
                "users",
                "{{userId}}"
              ]
            }
          },
          "response": []
        },
        {
          "name": "Change Password (admin override)",
          "event": [
            {
              "listen": "test",
              "script": {
                "exec": [
                  "pm.test('Status 200', () => pm.response.to.have.status(200));"
                ],
                "type": "text/javascript"
              }
            }
          ],
          "request": {
            "method": "PUT",
            "header": [
              {
                "key": "Authorization",
                "value": "Bearer {{token}}"
              },
              {
                "key": "Content-Type",
                "value": "application/json"
              }
            ],
            "body": {
              "mode": "raw",
              "raw": "{\n  \"current_password\": \"Nurse123!\",\n  \"new_password\": \"NewNurse456!\"\n}"
            },
            "url": {
              "raw": "{{baseUrl}}/users/{{userId}}/password",
              "host": [
                "{{baseUrl}}"
              ],
              "path": [
                "users",
                "{{userId}}",
                "password"
              ]
            }
          },
          "response": []
        }
      ]
    },
    {
      "name": "Reports",
      "item": [
        {
          "name": "Daily Summary",
          "event": [
            {
              "listen": "test",
              "script": {
                "exec": [
                  "pm.test('Status 200', () => pm.response.to.have.status(200));",
                  "pm.test('Returns summary object', () => {",
                  "  const json = pm.response.json();",
                  "  pm.expect(json).to.have.property('summary');",
                  "  pm.expect(json.summary).to.have.property('total_visits');",
                  "  pm.expect(json.summary).to.have.property('or_utilization_rate');",
                  "  pm.expect(json).to.have.property('by_stage');",
                  "});"
                ],
                "type": "text/javascript"
              }
            }
          ],
          "request": {
            "method": "GET",
            "header": [
              {
                "key": "Authorization",
                "value": "Bearer {{token}}"
              }
            ],
            "url": {
              "raw": "{{baseUrl}}/reports/daily-summary?date=2026-03-04",
              "host": [
                "{{baseUrl}}"
              ],
              "path": [
                "reports",
                "daily-summary"
              ],
              "query": [
                {
                  "key": "date",
                  "value": "2026-03-04"
                }
              ]
            }
          },
          "response": []
        },
        {
          "name": "Stage Duration",
          "event": [
            {
              "listen": "test",
              "script": {
                "exec": [
                  "pm.test('Status 200', () => pm.response.to.have.status(200));",
                  "pm.test('Returns stage_durations array', () => {",
                  "  const json = pm.response.json();",
                  "  pm.expect(json).to.have.property('stage_durations');",
                  "  pm.expect(json).to.have.property('period');",
                  "});"
                ],
                "type": "text/javascript"
              }
            }
          ],
          "request": {
            "method": "GET",
            "header": [
              {
                "key": "Authorization",
                "value": "Bearer {{token}}"
              }
            ],
            "url": {
              "raw": "{{baseUrl}}/reports/stage-duration?start_date=2026-03-01&end_date=2026-03-04",
              "host": [
                "{{baseUrl}}"
              ],
              "path": [
                "reports",
                "stage-duration"
              ],
              "query": [
                {
                  "key": "start_date",
                  "value": "2026-03-01"
                },
                {
                  "key": "end_date",
                  "value": "2026-03-04"
                }
              ]
            }
          },
          "response": []
        },
        {
          "name": "Stage Duration — missing dates (expect 400)",
          "event": [
            {
              "listen": "test",
              "script": {
                "exec": [
                  "pm.test('Status 400', () => pm.response.to.have.status(400));"
                ],
                "type": "text/javascript"
              }
            }
          ],
          "request": {
            "method": "GET",
            "header": [
              {
                "key": "Authorization",
                "value": "Bearer {{token}}"
              }
            ],
            "url": {
              "raw": "{{baseUrl}}/reports/stage-duration",
              "host": [
                "{{baseUrl}}"
              ],
              "path": [
                "reports",
                "stage-duration"
              ]
            }
          },
          "response": []
        }
      ]
    },
    {
      "name": "Security Checks",
      "item": [
        {
          "name": "Access protected route with no token (expect 401)",
          "event": [
            {
              "listen": "test",
              "script": {
                "exec": [
                  "pm.test('Status 401', () => pm.response.to.have.status(401));"
                ],
                "type": "text/javascript"
              }
            }
          ],
          "request": {
            "method": "GET",
            "header": [],
            "url": {
              "raw": "{{baseUrl}}/visits",
              "host": [
                "{{baseUrl}}"
              ],
              "path": [
                "visits"
              ]
            }
          },
          "response": []
        },
        {
          "name": "Access admin route with nurse token (expect 403)",
          "event": [
            {
              "listen": "pre-request",
              "script": {
                "exec": [
                  "// Log in as nurse first and save token to nurseToken variable",
                  "// then swap {{token}} to the nurse token before running this request"
                ],
                "type": "text/javascript"
              }
            },
            {
              "listen": "test",
              "script": {
                "exec": [
                  "pm.test('Status 403 — insufficient role', () => pm.response.to.have.status(403));"
                ],
                "type": "text/javascript"
              }
            }
          ],
          "request": {
            "method": "GET",
            "header": [
              {
                "key": "Authorization",
                "value": "Bearer {{token}}"
              }
            ],
            "url": {
              "raw": "{{baseUrl}}/reports/daily-summary",
              "host": [
                "{{baseUrl}}"
              ],
              "path": [
                "reports",
                "daily-summary"
              ]
            }
          },
          "response": []
        },
        {
          "name": "Access with malformed JWT (expect 401)",
          "event": [
            {
              "listen": "test",
              "script": {
                "exec": [
                  "pm.test('Status 401', () => pm.response.to.have.status(401));"
                ],
                "type": "text/javascript"
              }
            }
          ],
          "request": {
            "method": "GET",
            "header": [
              {
                "key": "Authorization",
                "value": "Bearer not.a.valid.jwt"
              }
            ],
            "url": {
              "raw": "{{baseUrl}}/visits",
              "host": [
                "{{baseUrl}}"
              ],
              "path": [
                "visits"
              ]
            }
          },
          "response": []
        }
      ]
    }
  ],
  "variable": [
    {
      "key": "baseUrl",
      "value": "http://localhost:3000/api",
      "type": "string"
    },
    {
      "key": "token",
      "value": "",
      "type": "string"
    },
    {
      "key": "visitId",
      "value": "1",
      "type": "string"
    },
    {
      "key": "roomId",
      "value": "1",
      "type": "string"
    },
    {
      "key": "userId",
      "value": "2",
      "type": "string"
    },
    {
      "key": "familyToken",
      "value": "",
      "type": "string"
    }
  ]
}